jupyterlite_xeus/__init__.py
jupyterlite_xeus/_pip.py
jupyterlite_xeus/_version.py
jupyterlite_xeus/add_on.py
jupyterlite_xeus/constants.py
jupyterlite_xeus/create_conda_env.py
jupyterlite_xeus-4.3.6.data/data/share/jupyter/labextensions/@jupyterlite/xeus/package.json
jupyterlite_xeus-4.3.6.data/data/share/jupyter/labextensions/@jupyterlite/xeus/static/565.b0cf79e34528738d26c8.js
jupyterlite_xeus-4.3.6.data/data/share/jupyter/labextensions/@jupyterlite/xeus/static/631.a88bd4f116523717808a.js
jupyterlite_xeus-4.3.6.data/data/share/jupyter/labextensions/@jupyterlite/xeus/static/652.b37dd672a553af1bcc54.js
jupyterlite_xeus-4.3.6.data/data/share/jupyter/labextensions/@jupyterlite/xeus/static/652.b37dd672a553af1bcc54.js.LICENSE.txt
jupyterlite_xeus-4.3.6.data/data/share/jupyter/labextensions/@jupyterlite/xeus/static/753.9cdbf81f5c121e139dec.js
jupyterlite_xeus-4.3.6.data/data/share/jupyter/labextensions/@jupyterlite/xeus/static/78.c18df1cd66aa8131a8a6.js
jupyterlite_xeus-4.3.6.data/data/share/jupyter/labextensions/@jupyterlite/xeus/static/961.5687e6a57912d6fd48f6.js
jupyterlite_xeus-4.3.6.data/data/share/jupyter/labextensions/@jupyterlite/xeus/static/remoteEntry.9d2830d8d2c3253ed9c6.js
jupyterlite_xeus-4.3.6.data/data/share/jupyter/labextensions/@jupyterlite/xeus/static/style.js
jupyterlite_xeus-4.3.6.data/data/share/jupyter/labextensions/@jupyterlite/xeus/static/third-party-licenses.json
jupyterlite_xeus-4.3.6.data/data/share/jupyter/labextensions/@jupyterlite/xeus/static/unpack-YMEPRZT6.wasm
jupyterlite_xeus-4.3.6.data/data/share/jupyter/labextensions/@jupyterlite/xeus/install.json
jupyterlite_xeus-4.3.6.dist-info/METADATA
jupyterlite_xeus-4.3.6.dist-info/WHEEL
jupyterlite_xeus-4.3.6.dist-info/entry_points.txt
jupyterlite_xeus-4.3.6.dist-info/licenses/LICENSE
jupyterlite_xeus-4.3.6.dist-info/RECORD
