Metadata-Version: 2.4
Name: jupyterlite_xeus
Version: 4.3.6
Dynamic: Keywords
Summary: JupyterLite loader for Xeus kernels
Project-URL: Homepage, https://github.com/jupyterlite/xeus
Project-URL: Bug Tracker, https://github.com/jupyterlite/xeus/issues
Project-URL: Repository, https://github.com/jupyterlite/xeus.git
Author: JupyterLite Contributors
License: BSD 3-Clause License
License-File: LICENSE
Classifier: Framework :: Jupyter
Classifier: Framework :: Jupyter :: JupyterLab
Classifier: Framework :: Jupyter :: JupyterLab :: 4
Classifier: Framework :: Jupyter :: JupyterLab :: Extensions
Classifier: Framework :: Jupyter :: JupyterLab :: Extensions :: Prebuilt
Classifier: License :: OSI Approved :: BSD License
Classifier: Programming Language :: Python
Classifier: Programming Language :: Python :: 3
Classifier: Programming Language :: Python :: 3.8
Classifier: Programming Language :: Python :: 3.9
Classifier: Programming Language :: Python :: 3.10
Classifier: Programming Language :: Python :: 3.11
Classifier: Programming Language :: Python :: 3.12
Classifier: Programming Language :: Python :: 3.13
Classifier: Programming Language :: Python :: 3.14
Requires-Python: >=3.8
Requires-Dist: empack<7,>=5.1.1
Requires-Dist: jupyterlite-core<0.8.0,>=0.7.0
Requires-Dist: pyyaml
Requires-Dist: requests
Requires-Dist: traitlets
